<?xml version="1.0" encoding="UTF-8" ?>
<class name="CassieSketchGraphEdge" inherits="Resource" api_type="core" xmlns:xsi="http://www.w3.org/2001/XMLSchema-instance" xsi:noNamespaceSchemaLocation="../../../doc/class.xsd">
	<brief_description>
	</brief_description>
	<description>
	</description>
	<tutorials>
	</tutorials>
	<methods>
		<method name="get_id" qualifiers="const">
			<return type="int" />
			<description>
			</description>
		</method>
		<method name="get_node_a_id" qualifiers="const">
			<return type="int" />
			<description>
			</description>
		</method>
		<method name="get_node_b_id" qualifiers="const">
			<return type="int" />
			<description>
			</description>
		</method>
		<method name="get_normals" qualifiers="const">
			<return type="PackedVector3Array" />
			<description>
			</description>
		</method>
		<method name="get_opposite" qualifiers="const">
			<return type="int" />
			<param index="0" name="node_id" type="int" />
			<description>
			</description>
		</method>
		<method name="get_points" qualifiers="const">
			<return type="PackedVector3Array" />
			<description>
			</description>
		</method>
		<method name="get_source_polyline_idx" qualifiers="const">
			<return type="int" />
			<description>
			</description>
		</method>
	</methods>
</class>
